frmodel/__init__.py
frmodel/base/__init__.py
frmodel/base/consts.py
frmodel/base/D2/__init__.py
frmodel/base/D2/draw2D.py
frmodel/base/D2/frame2D.py
frmodel/base/D2/kmeans2D.py
frmodel/base/D2/video2D.py
frmodel/base/D2/frame/__init__.py
frmodel/base/D2/frame/_frame_channel.py
frmodel/base/D2/frame/_frame_channel_fast_glcm.py
frmodel/base/D2/frame/_frame_channel_spec.py
frmodel/base/D2/frame/_frame_image.py
frmodel/base/D2/frame/_frame_loader.py
frmodel/base/D2/frame/_frame_partition.py
frmodel/base/D2/frame/_frame_plot.py
frmodel/base/D2/frame/_frame_scaling.py
frmodel/base/D2/frame/_frame_scoring.py
frmodel/base/D2/frame/glcm.cp38-win_amd64.pyd
frmodel/base/D2/frame/glcm2.c
frmodel/base/D2/frame/glcm2.cp38-win_amd64.pyd
frmodel/base/D2/frame/glcm2.pyx
frmodel/base/D3/__init__.py
frmodel/base/D3/cloud3D.py
frmodel/base/D3/cloud/__init__.py
frmodel/base/D3/cloud/_cloud_frame.py
frmodel/data/__init__.py
frmodel/data/load.py
frmodel/express/__init__.py
frmodel/express/channel/__init__.py
frmodel/express/channel/channel.py
frmodel/express/classification/__init__.py
frmodel/express/classification/classification.py
frmodel/express/examples/__init__.py
frmodel/express/examples/cloud3D_to_frame2D.py
frmodel/express/kmeans/__init__.py
frmodel/express/kmeans/_kmeans_scoring.py
frmodel/express/kmeans/kmeans_scoring.py
frmodel/express/mnl/__init__.py
frmodel/express/mnl/mnl.py
frmodel/express/scratches/__init__.py
frmodel/express/scratches/fingerprinting.py
frmodel/streamlit/__init__.py
frmodel/streamlit/unsupervised/__init__.py
frmodel/streamlit/unsupervised/analysis.py
frmodel/streamlit/unsupervised/glcm.py
frmodel/streamlit/unsupervised/processing.py
frmodel/streamlit/unsupervised/settings.py
src/frmodel/base/D2/frame/glcm2.cp38-win_amd64.pyd
frmodel-0.1.10.dist-info/METADATA
frmodel-0.1.10.dist-info/WHEEL
frmodel-0.1.10.dist-info/top_level.txt
frmodel-0.1.10.dist-info/RECORD
