Metadata-Version: 2.1
Name: frmodel
Version: 0.1.10
Summary: The base package to support frmodel data processing
Home-page: https://github.com/Eve-ning/frmodel
Author: Eve-ning
Author-email: dev_evening@hotmail.com
License: UNKNOWN
Platform: UNKNOWN
Classifier: Programming Language :: Python :: 3
Classifier: License :: OSI Approved :: MIT License
Classifier: Operating System :: OS Independent
Requires-Python: >=3.7
Requires-Dist: numpy
Requires-Dist: seaborn
Requires-Dist: sklearn
Requires-Dist: scikit-image
Requires-Dist: tqdm
Requires-Dist: plotly
Requires-Dist: opencv-python
Requires-Dist: imagecodecs
